modulus.v
module modulus(input [15:0] number,input [7:0] divider,output [7:0] mod);
  reg [15:0] numTemp;
  reg [7:0] divTemp;
  reg [7:0] modTemp;

  always @(*) begin
    divTemp=number / divider;
    numTemp=divTemp * divider;
    modTemp=number - numTemp;
  end
  assign mod=modTemp;
endmodule

EncDec.v
module EncDec(input [7:0]inp, input select, CLK, input [2:0] key, output [7:0] out);

  reg [1:0]state,nextstate;
  reg [15:0]intmidVal;
  wire [7:0]outVal;
  
  initial state=0;

  always @(posedge CLK)
    state<=nextstate;
    
  always @(posedge CLK) begin
    case(state)
      0: 
      begin
        if (inp==0 && key==0) 
          nextstate<=0;
        else
          nextstate<=1;
      end
      1:
      begin
        if (select==0)
          nextstate<=2;
        else
          nextstate<=3;
      end
      2:
      begin
        intmidVal=inp+key;
        nextstate=4;
      end
      3:
      begin
        intmidVal=inp-key;
        nextstate=4;
      end
      4:
      nextstate=0;
    endcase
  end
  
  modulus uut(.number(intmidVal),.divider(128),.mod(outVal));
  
  assign out=outVal;
endmodule

EncDecTB.v
module EncDecTB();
  reg [7:0]num;
  reg clk,sel;
  reg [2:0]ky;
  wire [7:0]outval;
  
  EncDec uut(.inp(num),.select(sel),.CLK(clk),.key(ky),.out(outval));
  
  initial begin
    $dumpfile("EncDec.vcd");
    $dumpvars(0,uut);
    $monitor("clock=%b number=%c, select=%d, key=%d out=%d",clk,num,sel,ky,outval);
    
    #0 clk=0;num=65;sel=1;ky=3;
    #5 sel=1;
    #5 num=91;
    #10 $finish;
  end
  always #1  clk=!clk;
endmodule

EncDec.vcd
$date
	Sun Jun  7 22:46:29 2015
$end
$version
	Icarus Verilog
$end
$timescale
	1s
$end
$scope module EncDecTB $end
$scope module uut $end
$var wire 1 ! CLK $end
$var wire 8 " inp [7:0] $end
$var wire 3 # key [2:0] $end
$var wire 8 $ out [7:0] $end
$var wire 8 % outVal [7:0] $end
$var wire 1 & select $end
$var reg 16 ' intmidVal [15:0] $end
$var reg 2 ( nextstate [1:0] $end
$var reg 2 ) state [1:0] $end
$scope module uut $end
$var wire 8 * divider [7:0] $end
$var wire 8 + mod [7:0] $end
$var wire 16 , number [15:0] $end
$var reg 8 - divTemp [7:0] $end
$var reg 8 . modTemp [7:0] $end
$var reg 16 / numTemp [15:0] $end
$upscope $end
$upscope $end
$upscope $end
$enddefinitions $end
#0
$dumpvars
bx /
bx .
bx -
bx ,
bx +
b10000000 *
b0 )
bx (
bx '
1&
bx %
bx $
b11 #
b1000001 "
0!
$end
#1
bx )
b1 (
1!
#2
0!
#3
b1 )
1!
#4
0!
#5
b11 (
1!
#6
0!
#7
b11 )
1!
#8
0!
#9
b0 )
b111110 .
b111110 %
b111110 +
b111110 $
b0 /
b0 -
b0 (
b111110 '
b111110 ,
1!
#10
0!
b1011011 "
#11
b1 (
1!
#12
0!
#13
b1 )
1!
#14
0!
#15
b11 (
1!
#16
0!
#17
b11 )
1!
#18
0!
#19
b1011000 .
b1011000 %
b1011000 +
b1011000 $
b0 (
b1011000 '
b1011000 ,
1!
